rechat/cli.py
rechat/debug.py
rechat/marker.py
rechat/replayer.py
rechat-0.1.7.dist-info/METADATA
rechat-0.1.7.dist-info/WHEEL
rechat-0.1.7.dist-info/entry_points.txt
rechat-0.1.7.dist-info/top_level.txt
rechat-0.1.7.dist-info/RECORD
