Metadata-Version: 2.4
Name: rechat
Version: 0.1.7
Summary: Caching and replaying man-in-the-middle proxy for OpenAI APIs
Requires-Python: >=3.9
Requires-Dist: mitmproxy
Requires-Dist: tqdm
Requires-Dist: md2term
